qgis_plugin_repo/__init__.py
qgis_plugin_repo/cli.py
qgis_plugin_repo/merger.py
qgis_plugin_repo-0.0.0.dist-info/METADATA
qgis_plugin_repo-0.0.0.dist-info/WHEEL
qgis_plugin_repo-0.0.0.dist-info/entry_points.txt
qgis_plugin_repo-0.0.0.dist-info/top_level.txt
qgis_plugin_repo-0.0.0.dist-info/RECORD
