Metadata-Version: 1.2
Name: qgis-plugin-repo
Version: 0.0.0
Summary: Manipulate a QGIS Plugin repository.
Home-page: UNKNOWN
Author: Etienne Trimaille
Author-email: etrimaille@3liz.com
License: UNKNOWN
Keywords: QGIS
Platform: UNKNOWN
Classifier: Topic :: Scientific/Engineering :: GIS
Classifier: License :: OSI Approved :: GNU General Public License v3 or later (GPLv3+)
Classifier: Intended Audience :: System Administrators
Classifier: Intended Audience :: Information Technology
Requires-Python: >=3.7
